sjlang/__init__.py
sjlang/sjlang.py
sjlang-1.2.dist-info/METADATA
sjlang-1.2.dist-info/WHEEL
sjlang-1.2.dist-info/top_level.txt
sjlang-1.2.dist-info/RECORD
