Metadata-Version: 2.1
Name: sjlang
Version: 1.2
Summary: it's very cool korean lang
Home-page: https://github.com/sejin0104/sejinjin-lang
Author: Sejinjin
Author-email: sejinjin1101@gmail.com
License: MIT
Keywords: sejinjin,language,funny
Classifier: Programming Language :: Python :: 3
Classifier: License :: OSI Approved :: MIT License
Classifier: Operating System :: OS Independent
